[{"game_id": "824257", "date": "2026-06-27", "home_team": "Detroit Tigers", "away_team": "Houston Astros", "home_pitcher": 664285, "away_pitcher": 678906, "game_time": "2026-06-27T17:10:00Z", "status": "live"}, {"game_id": "824745", "date": "2026-06-27", "home_team": "Boston Red Sox", "away_team": "New York Yankees", "home_pitcher": 687562, "away_pitcher": 543037, "game_time": "2026-06-27T17:10:00Z", "status": "live"}, {"game_id": "822794", "date": "2026-06-27", "home_team": "Toronto Blue Jays", "away_team": "Texas Rangers", "home_pitcher": 656302, "away_pitcher": 615698, "game_time": "2026-06-27T19:07:00Z", "status": "preview"}, {"game_id": "823364", "date": "2026-06-27", "home_team": "Pittsburgh Pirates", "away_team": "Cincinnati Reds", "home_pitcher": 683003, "away_pitcher": 695505, "game_time": "2026-06-27T20:05:00Z", "status": "preview"}, {"game_id": "823609", "date": "2026-06-27", "home_team": "New York Mets", "away_team": "Philadelphia Phillies", "home_pitcher": 681035, "away_pitcher": 641835, "game_time": "2026-06-27T20:10:00Z", "status": "preview"}, {"game_id": "824581", "date": "2026-06-27", "home_team": "Chicago White Sox", "away_team": "Kansas City Royals", "home_pitcher": 663436, "away_pitcher": 608379, "game_time": "2026-06-27T20:10:00Z", "status": "preview"}, {"game_id": "822960", "date": "2026-06-27", "home_team": "Tampa Bay Rays", "away_team": "Arizona Diamondbacks", "home_pitcher": 642121, "away_pitcher": 703615, "game_time": "2026-06-27T22:10:00Z", "status": "preview"}, {"game_id": "824825", "date": "2026-06-27", "home_team": "Baltimore Orioles", "away_team": "Washington Nationals", "home_pitcher": 687064, "away_pitcher": 656492, "game_time": "2026-06-27T23:05:00Z", "status": "preview"}, {"game_id": "824421", "date": "2026-06-27", "home_team": "Cleveland Guardians", "away_team": "Seattle Mariners", "home_pitcher": 677944, "away_pitcher": 669302, "game_time": "2026-06-27T23:10:00Z", "status": "preview"}, {"game_id": "823689", "date": "2026-06-27", "home_team": "Minnesota Twins", "away_team": "Colorado Rockies", "home_pitcher": 702474, "away_pitcher": 547179, "game_time": "2026-06-27T23:10:00Z", "status": "preview"}, {"game_id": "823770", "date": "2026-06-27", "home_team": "Milwaukee Brewers", "away_team": "Chicago Cubs", "home_pitcher": 690986, "away_pitcher": 656849, "game_time": "2026-06-27T23:10:00Z", "status": "preview"}, {"game_id": "823038", "date": "2026-06-27", "home_team": "St. Louis Cardinals", "away_team": "Miami Marlins", "home_pitcher": 669467, "away_pitcher": 687473, "game_time": "2026-06-27T23:15:00Z", "status": "preview"}, {"game_id": "823283", "date": "2026-06-27", "home_team": "San Diego Padres", "away_team": "Los Angeles Dodgers", "home_pitcher": 681190, "away_pitcher": 808967, "game_time": "2026-06-28T00:40:00Z", "status": "preview"}, {"game_id": "823207", "date": "2026-06-27", "home_team": "San Francisco Giants", "away_team": "Atlanta Braves", "home_pitcher": 657277, "away_pitcher": 693821, "game_time": "2026-06-28T01:05:00Z", "status": "preview"}, {"game_id": "824015", "date": "2026-06-27", "home_team": "Los Angeles Angels", "away_team": "Athletics", "home_pitcher": 672282, "away_pitcher": 678022, "game_time": "2026-06-28T01:38:00Z", "status": "preview"}]