[{"player": "Sam Aldegheri", "team": "Los Angeles Angels", "opponent": "Athletics", "game_id": "824011", "prop_type": "pitcher_strikeouts", "pick": "UNDER 4.5", "projected": 2.42, "model_prob": 0.856, "prob_pct": 85.6, "odds": null, "book": null, "fair_prob": null, "value_edge": null, "kelly": null, "has_line": false, "is_edge": false, "confidence": "HIGH", "bvp_flag": null, "generated_at": "2026-06-28"}, {"player": "Gavin Williams", "team": "Cleveland Guardians", "opponent": "Seattle Mariners", "game_id": "824422", "prop_type": "pitcher_strikeouts", "pick": "UNDER 6.5", "projected": 4.9, "model_prob": 0.762, "prob_pct": 76.2, "odds": 110, "book": "fanduel", "fair_prob": 0.454, "value_edge": 0.678, "kelly": 0.25, "has_line": true, "is_edge": true, "confidence": "HIGH", "bvp_flag": "lineup_kr_0.188_n0.852", "generated_at": "2026-06-28"}, {"player": "Ryan Feltner", "team": "Colorado Rockies", "opponent": "Minnesota Twins", "game_id": "823686", "prop_type": "pitcher_strikeouts", "pick": "UNDER 4.5", "projected": 3.29, "model_prob": 0.742, "prob_pct": 74.2, "odds": -172, "book": "fanduel", "fair_prob": 0.59, "value_edge": 0.257, "kelly": 0.25, "has_line": true, "is_edge": true, "confidence": "HIGH", "bvp_flag": null, "generated_at": "2026-06-28"}, {"player": "Aaron Civale", "team": "Athletics", "opponent": "Los Angeles Angels", "game_id": "824011", "prop_type": "pitcher_strikeouts", "pick": "UNDER 4.5", "projected": 3.43, "model_prob": 0.728, "prob_pct": 72.8, "odds": -154, "book": "fanduel", "fair_prob": 0.567, "value_edge": 0.284, "kelly": 0.25, "has_line": true, "is_edge": true, "confidence": "HIGH", "bvp_flag": null, "generated_at": "2026-06-28"}, {"player": "Carlos Rod\u00f3n", "team": "New York Yankees", "opponent": "Boston Red Sox", "game_id": "824744", "prop_type": "pitcher_strikeouts", "pick": "OVER 4.5", "projected": 5.72, "model_prob": 0.68, "prob_pct": 68.0, "odds": null, "book": null, "fair_prob": null, "value_edge": null, "kelly": null, "has_line": false, "is_edge": false, "confidence": "MEDIUM", "bvp_flag": null, "generated_at": "2026-06-28"}, {"player": "Los Angeles Dodgers", "team": "Los Angeles Dodgers", "opponent": "San Diego Padres", "game_id": "823281", "prop_type": "moneyline", "pick": "Los Angeles Dodgers ML", "projected": 0.66, "model_prob": 0.661, "prob_pct": 66.1, "odds": -142, "book": "fanduel", "fair_prob": 0.563, "value_edge": 0.173, "kelly": 0.179, "has_line": true, "is_edge": true, "confidence": "MEDIUM", "bvp_flag": null, "generated_at": "2026-06-28"}, {"player": "Jes\u00fas Luzardo", "team": "Philadelphia Phillies", "opponent": "New York Mets", "game_id": "823608", "prop_type": "pitcher_strikeouts", "pick": "OVER 4.5", "projected": 5.72, "model_prob": 0.651, "prob_pct": 65.1, "odds": null, "book": null, "fair_prob": null, "value_edge": null, "kelly": null, "has_line": false, "is_edge": false, "confidence": "MEDIUM", "bvp_flag": "lineup_kr_0.132_n0.85", "generated_at": "2026-06-28"}, {"player": "Milwaukee Brewers", "team": "Milwaukee Brewers", "opponent": "Chicago Cubs", "game_id": "823769", "prop_type": "moneyline", "pick": "Milwaukee Brewers ML", "projected": 0.65, "model_prob": 0.645, "prob_pct": 64.5, "odds": -162, "book": "fanduel", "fair_prob": 0.593, "value_edge": 0.087, "kelly": 0.07, "has_line": true, "is_edge": true, "confidence": "LOW", "bvp_flag": null, "generated_at": "2026-06-28"}, {"player": "Kumar Rocker", "team": "Texas Rangers", "opponent": "Toronto Blue Jays", "game_id": "822795", "prop_type": "pitcher_strikeouts", "pick": "OVER 3.5", "projected": 4.56, "model_prob": 0.645, "prob_pct": 64.5, "odds": -152, "book": "fanduel", "fair_prob": 0.563, "value_edge": 0.145, "kelly": 0.1054, "has_line": true, "is_edge": true, "confidence": "MEDIUM", "bvp_flag": null, "generated_at": "2026-06-28"}, {"player": "Atlanta Braves", "team": "Atlanta Braves", "opponent": "San Francisco Giants", "game_id": "823204", "prop_type": "moneyline", "pick": "Atlanta Braves ML", "projected": 0.64, "model_prob": 0.641, "prob_pct": 64.1, "odds": -176, "book": "fanduel", "fair_prob": 0.613, "value_edge": 0.047, "kelly": 0.01, "has_line": true, "is_edge": false, "confidence": "LOW", "bvp_flag": null, "generated_at": "2026-06-28"}, {"player": "Chicago White Sox", "team": "Chicago White Sox", "opponent": "Kansas City Royals", "game_id": "824580", "prop_type": "moneyline", "pick": "Chicago White Sox ML", "projected": 0.64, "model_prob": 0.64, "prob_pct": 64.0, "odds": -138, "book": "fanduel", "fair_prob": 0.558, "value_edge": 0.147, "kelly": 0.1442, "has_line": true, "is_edge": true, "confidence": "LOW", "bvp_flag": null, "generated_at": "2026-06-28"}, {"player": "Pittsburgh Pirates", "team": "Pittsburgh Pirates", "opponent": "Cincinnati Reds", "game_id": "823362", "prop_type": "moneyline", "pick": "Pittsburgh Pirates ML", "projected": 0.62, "model_prob": 0.618, "prob_pct": 61.8, "odds": -220, "book": "fanduel", "fair_prob": 0.648, "value_edge": -0.046, "kelly": 0.0, "has_line": true, "is_edge": false, "confidence": "LOW", "bvp_flag": null, "generated_at": "2026-06-28"}, {"player": "Hunter Brown", "team": "Houston Astros", "opponent": "Detroit Tigers", "game_id": "824256", "prop_type": "pitcher_strikeouts", "pick": "OVER 6.5", "projected": 7.31, "model_prob": 0.613, "prob_pct": 61.3, "odds": -144, "book": "fanduel", "fair_prob": 0.551, "value_edge": 0.112, "kelly": 0.0557, "has_line": true, "is_edge": true, "confidence": "LOW", "bvp_flag": "lineup_kr_0.286_n1.15", "generated_at": "2026-06-28"}, {"player": "Emmet Sheehan", "team": "Los Angeles Dodgers", "opponent": "San Diego Padres", "game_id": "823281", "prop_type": "pitcher_strikeouts", "pick": "UNDER 5.5", "projected": 4.98, "model_prob": 0.607, "prob_pct": 60.7, "odds": -114, "book": "fanduel", "fair_prob": 0.5, "value_edge": 0.214, "kelly": 0.159, "has_line": true, "is_edge": true, "confidence": "LOW", "bvp_flag": null, "generated_at": "2026-06-28"}, {"player": "Colt Keith", "team": "Detroit Tigers", "opponent": "Houston Astros", "game_id": "824256", "prop_type": "batter_hits", "pick": "OVER 0.5", "projected": 0.74, "model_prob": 0.603, "prob_pct": 60.3, "odds": null, "book": null, "fair_prob": null, "value_edge": null, "kelly": null, "has_line": false, "is_edge": false, "confidence": "LOW", "bvp_flag": "sum_strong", "generated_at": "2026-06-28"}, {"player": "Tampa Bay Rays", "team": "Tampa Bay Rays", "opponent": "Arizona Diamondbacks", "game_id": "822959", "prop_type": "moneyline", "pick": "Tampa Bay Rays ML", "projected": 0.6, "model_prob": 0.597, "prob_pct": 59.7, "odds": -440, "book": "fanduel", "fair_prob": 0.77, "value_edge": -0.224, "kelly": 0.0, "has_line": true, "is_edge": false, "confidence": "LOW", "bvp_flag": null, "generated_at": "2026-06-28"}, {"player": "Connor Prielipp", "team": "Minnesota Twins", "opponent": "Colorado Rockies", "game_id": "823686", "prop_type": "pitcher_strikeouts", "pick": "UNDER 5.5", "projected": 4.97, "model_prob": 0.596, "prob_pct": 59.6, "odds": -128, "book": "fanduel", "fair_prob": 0.534, "value_edge": 0.116, "kelly": 0.0789, "has_line": true, "is_edge": true, "confidence": "LOW", "bvp_flag": null, "generated_at": "2026-06-28"}, {"player": "Minnesota Twins", "team": "Minnesota Twins", "opponent": "Colorado Rockies", "game_id": "823686", "prop_type": "moneyline", "pick": "Minnesota Twins ML", "projected": 0.6, "model_prob": 0.595, "prob_pct": 59.5, "odds": -164, "book": "fanduel", "fair_prob": 0.597, "value_edge": -0.002, "kelly": 0.0, "has_line": true, "is_edge": false, "confidence": "LOW", "bvp_flag": null, "generated_at": "2026-06-28"}, {"player": "Matt Vierling", "team": "Detroit Tigers", "opponent": "Houston Astros", "game_id": "824256", "prop_type": "batter_hits", "pick": "OVER 0.5", "projected": 0.78, "model_prob": 0.594, "prob_pct": 59.4, "odds": null, "book": null, "fair_prob": null, "value_edge": null, "kelly": null, "has_line": false, "is_edge": false, "confidence": "LOW", "bvp_flag": "sum_good", "generated_at": "2026-06-28"}, {"player": "Luis Arraez", "team": "San Francisco Giants", "opponent": "Atlanta Braves", "game_id": "823204", "prop_type": "batter_hits", "pick": "OVER 0.5", "projected": 0.85, "model_prob": 0.593, "prob_pct": 59.3, "odds": null, "book": null, "fair_prob": null, "value_edge": null, "kelly": null, "has_line": false, "is_edge": false, "confidence": "LOW", "bvp_flag": "sum_lean", "generated_at": "2026-06-28"}, {"player": "Taylor Ward", "team": "Baltimore Orioles", "opponent": "Washington Nationals", "game_id": "824821", "prop_type": "batter_hits", "pick": "OVER 0.5", "projected": 0.68, "model_prob": 0.592, "prob_pct": 59.2, "odds": null, "book": null, "fair_prob": null, "value_edge": null, "kelly": null, "has_line": false, "is_edge": false, "confidence": "LOW", "bvp_flag": "sum_premium", "generated_at": "2026-06-28"}, {"player": "New York Yankees", "team": "New York Yankees", "opponent": "Boston Red Sox", "game_id": "824744", "prop_type": "moneyline", "pick": "New York Yankees ML", "projected": 0.59, "model_prob": 0.589, "prob_pct": 58.9, "odds": -102, "book": "fanduel", "fair_prob": 0.485, "value_edge": 0.216, "kelly": 0.1705, "has_line": true, "is_edge": true, "confidence": "LOW", "bvp_flag": null, "generated_at": "2026-06-28"}, {"player": "Detroit Tigers", "team": "Detroit Tigers", "opponent": "Houston Astros", "game_id": "824256", "prop_type": "moneyline", "pick": "Detroit Tigers ML", "projected": 0.58, "model_prob": 0.584, "prob_pct": 58.4, "odds": -111, "book": "fanduel", "fair_prob": 0.496, "value_edge": 0.177, "kelly": 0.1214, "has_line": true, "is_edge": true, "confidence": "LOW", "bvp_flag": null, "generated_at": "2026-06-28"}, {"player": "Henry Davis", "team": "Pittsburgh Pirates", "opponent": "Cincinnati Reds", "game_id": "823362", "prop_type": "batter_hits", "pick": "OVER 0.5", "projected": 0.65, "model_prob": 0.578, "prob_pct": 57.8, "odds": null, "book": null, "fair_prob": null, "value_edge": null, "kelly": null, "has_line": false, "is_edge": false, "confidence": "LOW", "bvp_flag": "sum_premium", "generated_at": "2026-06-28"}, {"player": "Lourdes Gurriel Jr.", "team": "Arizona Diamondbacks", "opponent": "Tampa Bay Rays", "game_id": "822959", "prop_type": "batter_hits", "pick": "OVER 0.5", "projected": 0.75, "model_prob": 0.578, "prob_pct": 57.8, "odds": null, "book": null, "fair_prob": null, "value_edge": null, "kelly": null, "has_line": false, "is_edge": false, "confidence": "LOW", "bvp_flag": "sum_good", "generated_at": "2026-06-28"}, {"player": "Otto Lopez", "team": "Miami Marlins", "opponent": "St. Louis Cardinals", "game_id": "823037", "prop_type": "batter_hits", "pick": "OVER 0.5", "projected": 0.74, "model_prob": 0.572, "prob_pct": 57.2, "odds": null, "book": null, "fair_prob": null, "value_edge": null, "kelly": null, "has_line": false, "is_edge": false, "confidence": "LOW", "bvp_flag": "sum_good", "generated_at": "2026-06-28"}, {"player": "Keibert Ruiz", "team": "Washington Nationals", "opponent": "Baltimore Orioles", "game_id": "824821", "prop_type": "batter_hits", "pick": "OVER 0.5", "projected": 0.64, "model_prob": 0.571, "prob_pct": 57.1, "odds": null, "book": null, "fair_prob": null, "value_edge": null, "kelly": null, "has_line": false, "is_edge": false, "confidence": "LOW", "bvp_flag": "sum_premium", "generated_at": "2026-06-28"}, {"player": "Luis Torrens", "team": "New York Mets", "opponent": "Philadelphia Phillies", "game_id": "823608", "prop_type": "batter_hits", "pick": "OVER 0.5", "projected": 0.8, "model_prob": 0.57, "prob_pct": 57.0, "odds": null, "book": null, "fair_prob": null, "value_edge": null, "kelly": null, "has_line": false, "is_edge": false, "confidence": "LOW", "bvp_flag": "sum_lean", "generated_at": "2026-06-28"}, {"player": "Jackson Merrill", "team": "San Diego Padres", "opponent": "Los Angeles Dodgers", "game_id": "823281", "prop_type": "batter_hits", "pick": "OVER 0.5", "projected": 0.83, "model_prob": 0.565, "prob_pct": 56.5, "odds": null, "book": null, "fair_prob": null, "value_edge": null, "kelly": null, "has_line": false, "is_edge": false, "confidence": "LOW", "bvp_flag": "none", "generated_at": "2026-06-28"}, {"player": "Brayan Rocchio", "team": "Cleveland Guardians", "opponent": "Seattle Mariners", "game_id": "824422", "prop_type": "batter_hits", "pick": "OVER 0.5", "projected": 0.71, "model_prob": 0.559, "prob_pct": 55.9, "odds": null, "book": null, "fair_prob": null, "value_edge": null, "kelly": null, "has_line": false, "is_edge": false, "confidence": "LOW", "bvp_flag": "sum_good", "generated_at": "2026-06-28"}, {"player": "Tyler Freeman", "team": "Colorado Rockies", "opponent": "Minnesota Twins", "game_id": "823686", "prop_type": "batter_hits", "pick": "OVER 0.5", "projected": 0.81, "model_prob": 0.556, "prob_pct": 55.6, "odds": null, "book": null, "fair_prob": null, "value_edge": null, "kelly": null, "has_line": false, "is_edge": false, "confidence": "LOW", "bvp_flag": null, "generated_at": "2026-06-28"}, {"player": "Jeff McNeil", "team": "Athletics", "opponent": "Los Angeles Angels", "game_id": "824011", "prop_type": "batter_hits", "pick": "OVER 0.5", "projected": 0.81, "model_prob": 0.553, "prob_pct": 55.3, "odds": null, "book": null, "fair_prob": null, "value_edge": null, "kelly": null, "has_line": false, "is_edge": false, "confidence": "LOW", "bvp_flag": null, "generated_at": "2026-06-28"}, {"player": "Justin Crawford", "team": "Philadelphia Phillies", "opponent": "New York Mets", "game_id": "823608", "prop_type": "batter_hits", "pick": "OVER 0.5", "projected": 0.8, "model_prob": 0.551, "prob_pct": 55.1, "odds": null, "book": null, "fair_prob": null, "value_edge": null, "kelly": null, "has_line": false, "is_edge": false, "confidence": "LOW", "bvp_flag": "none", "generated_at": "2026-06-28"}, {"player": "Taylor Ward", "team": "Baltimore Orioles", "opponent": "Washington Nationals", "game_id": "824821", "prop_type": "batter_home_runs", "pick": "OVER 0.5", "projected": 1.61, "model_prob": 0.444, "prob_pct": 44.4, "odds": null, "book": null, "fair_prob": null, "value_edge": null, "kelly": null, "has_line": false, "is_edge": false, "confidence": "HIGH", "bvp_flag": "hr_score_1.613_hr_elite", "generated_at": "2026-06-28"}, {"player": "Bryan Reynolds", "team": "Pittsburgh Pirates", "opponent": "Cincinnati Reds", "game_id": "823362", "prop_type": "batter_home_runs", "pick": "OVER 0.5", "projected": 1.61, "model_prob": 0.444, "prob_pct": 44.4, "odds": null, "book": null, "fair_prob": null, "value_edge": null, "kelly": null, "has_line": false, "is_edge": false, "confidence": "HIGH", "bvp_flag": "hr_score_1.613_hr_elite", "generated_at": "2026-06-28"}, {"player": "Ryan O'Hearn", "team": "Pittsburgh Pirates", "opponent": "Cincinnati Reds", "game_id": "823362", "prop_type": "batter_home_runs", "pick": "OVER 0.5", "projected": 1.57, "model_prob": 0.444, "prob_pct": 44.4, "odds": null, "book": null, "fair_prob": null, "value_edge": null, "kelly": null, "has_line": false, "is_edge": false, "confidence": "HIGH", "bvp_flag": "hr_score_1.57_hr_elite", "generated_at": "2026-06-28"}, {"player": "Henry Davis", "team": "Pittsburgh Pirates", "opponent": "Cincinnati Reds", "game_id": "823362", "prop_type": "batter_home_runs", "pick": "OVER 0.5", "projected": 1.77, "model_prob": 0.444, "prob_pct": 44.4, "odds": null, "book": null, "fair_prob": null, "value_edge": null, "kelly": null, "has_line": false, "is_edge": false, "confidence": "HIGH", "bvp_flag": "hr_score_1.769_hr_elite", "generated_at": "2026-06-28"}, {"player": "Jake Burger", "team": "Texas Rangers", "opponent": "Toronto Blue Jays", "game_id": "822795", "prop_type": "batter_home_runs", "pick": "OVER 0.5", "projected": 1.6, "model_prob": 0.444, "prob_pct": 44.4, "odds": null, "book": null, "fair_prob": null, "value_edge": null, "kelly": null, "has_line": false, "is_edge": false, "confidence": "HIGH", "bvp_flag": "hr_score_1.601_hr_elite", "generated_at": "2026-06-28"}, {"player": "Eric Wagaman", "team": "New York Mets", "opponent": "Philadelphia Phillies", "game_id": "823608", "prop_type": "batter_home_runs", "pick": "OVER 0.5", "projected": 1.55, "model_prob": 0.444, "prob_pct": 44.4, "odds": null, "book": null, "fair_prob": null, "value_edge": null, "kelly": null, "has_line": false, "is_edge": false, "confidence": "HIGH", "bvp_flag": "hr_score_1.551_hr_elite", "generated_at": "2026-06-28"}, {"player": "Kyle Schwarber", "team": "Philadelphia Phillies", "opponent": "New York Mets", "game_id": "823608", "prop_type": "batter_home_runs", "pick": "OVER 0.5", "projected": 1.75, "model_prob": 0.444, "prob_pct": 44.4, "odds": null, "book": null, "fair_prob": null, "value_edge": null, "kelly": null, "has_line": false, "is_edge": false, "confidence": "HIGH", "bvp_flag": "hr_score_1.749_hr_elite", "generated_at": "2026-06-28"}, {"player": "Bryce Harper", "team": "Philadelphia Phillies", "opponent": "New York Mets", "game_id": "823608", "prop_type": "batter_home_runs", "pick": "OVER 0.5", "projected": 1.77, "model_prob": 0.444, "prob_pct": 44.4, "odds": null, "book": null, "fair_prob": null, "value_edge": null, "kelly": null, "has_line": false, "is_edge": false, "confidence": "HIGH", "bvp_flag": "hr_score_1.774_hr_elite", "generated_at": "2026-06-28"}, {"player": "Seiya Suzuki", "team": "Chicago Cubs", "opponent": "Milwaukee Brewers", "game_id": "823769", "prop_type": "batter_home_runs", "pick": "OVER 0.5", "projected": 1.6, "model_prob": 0.444, "prob_pct": 44.4, "odds": null, "book": null, "fair_prob": null, "value_edge": null, "kelly": null, "has_line": false, "is_edge": false, "confidence": "HIGH", "bvp_flag": "hr_score_1.599_hr_elite", "generated_at": "2026-06-28"}, {"player": "Dansby Swanson", "team": "Chicago Cubs", "opponent": "Milwaukee Brewers", "game_id": "823769", "prop_type": "batter_home_runs", "pick": "OVER 0.5", "projected": 1.58, "model_prob": 0.444, "prob_pct": 44.4, "odds": null, "book": null, "fair_prob": null, "value_edge": null, "kelly": null, "has_line": false, "is_edge": false, "confidence": "HIGH", "bvp_flag": "hr_score_1.582_hr_elite", "generated_at": "2026-06-28"}, {"player": "Manny Machado", "team": "San Diego Padres", "opponent": "Los Angeles Dodgers", "game_id": "823281", "prop_type": "batter_home_runs", "pick": "OVER 0.5", "projected": 1.75, "model_prob": 0.444, "prob_pct": 44.4, "odds": null, "book": null, "fair_prob": null, "value_edge": null, "kelly": null, "has_line": false, "is_edge": false, "confidence": "HIGH", "bvp_flag": "hr_score_1.752_hr_elite", "generated_at": "2026-06-28"}, {"player": "Shohei Ohtani", "team": "Los Angeles Dodgers", "opponent": "San Diego Padres", "game_id": "823281", "prop_type": "batter_home_runs", "pick": "OVER 0.5", "projected": 1.76, "model_prob": 0.444, "prob_pct": 44.4, "odds": null, "book": null, "fair_prob": null, "value_edge": null, "kelly": null, "has_line": false, "is_edge": false, "confidence": "HIGH", "bvp_flag": "hr_score_1.764_hr_elite", "generated_at": "2026-06-28"}, {"player": "Luis Garc\u00eda Jr.", "team": "Washington Nationals", "opponent": "Baltimore Orioles", "game_id": "824821", "prop_type": "batter_home_runs", "pick": "OVER 0.5", "projected": 1.32, "model_prob": 0.419, "prob_pct": 41.9, "odds": null, "book": null, "fair_prob": null, "value_edge": null, "kelly": null, "has_line": false, "is_edge": false, "confidence": "MEDIUM", "bvp_flag": "hr_score_1.321_hr_strong", "generated_at": "2026-06-28"}, {"player": "Spencer Steer", "team": "Cincinnati Reds", "opponent": "Pittsburgh Pirates", "game_id": "823362", "prop_type": "batter_home_runs", "pick": "OVER 0.5", "projected": 1.33, "model_prob": 0.419, "prob_pct": 41.9, "odds": null, "book": null, "fair_prob": null, "value_edge": null, "kelly": null, "has_line": false, "is_edge": false, "confidence": "MEDIUM", "bvp_flag": "hr_score_1.334_hr_strong", "generated_at": "2026-06-28"}, {"player": "Yandy D\u00edaz", "team": "Tampa Bay Rays", "opponent": "Arizona Diamondbacks", "game_id": "822959", "prop_type": "batter_home_runs", "pick": "OVER 0.5", "projected": 1.41, "model_prob": 0.419, "prob_pct": 41.9, "odds": null, "book": null, "fair_prob": null, "value_edge": null, "kelly": null, "has_line": false, "is_edge": false, "confidence": "MEDIUM", "bvp_flag": "hr_score_1.41_hr_strong", "generated_at": "2026-06-28"}, {"player": "Mookie Betts", "team": "Los Angeles Dodgers", "opponent": "San Diego Padres", "game_id": "823281", "prop_type": "batter_home_runs", "pick": "OVER 0.5", "projected": 1.49, "model_prob": 0.419, "prob_pct": 41.9, "odds": null, "book": null, "fair_prob": null, "value_edge": null, "kelly": null, "has_line": false, "is_edge": false, "confidence": "MEDIUM", "bvp_flag": "hr_score_1.489_hr_strong", "generated_at": "2026-06-28"}]