[
  {
    "player": "Luis Arraez",
    "team": "San Francisco Giants",
    "opponent": "Colorado Rockies",
    "prop_type": "hits",
    "pick": "OVER 0.5",
    "projected": 1.3,
    "model_prob": 0.728,
    "fair_prob": 0.285,
    "odds": 230,
    "value_edge": 1.558,
    "kelly_fraction": 0.25,
    "confidence": "HIGH",
    "generated_at": "2026-05-31"
  },
  {
    "player": "Willy Adames",
    "team": "San Francisco Giants",
    "opponent": "Colorado Rockies",
    "prop_type": "hits",
    "pick": "OVER 0.5",
    "projected": 1.02,
    "model_prob": 0.639,
    "fair_prob": 0.261,
    "odds": 260,
    "value_edge": 1.45,
    "kelly_fraction": 0.25,
    "confidence": "HIGH",
    "generated_at": "2026-05-31"
  },
  {
    "player": "Mookie Betts",
    "team": "Los Angeles Dodgers",
    "opponent": "Philadelphia Phillies",
    "prop_type": "hits",
    "pick": "UNDER 1.5",
    "projected": 0.72,
    "model_prob": 0.836,
    "fair_prob": 0.426,
    "odds": 130,
    "value_edge": 0.964,
    "kelly_fraction": 0.25,
    "confidence": "HIGH",
    "generated_at": "2026-05-31"
  },
  {
    "player": "Bryan Woo",
    "team": "Seattle Mariners",
    "opponent": "Arizona Diamondbacks",
    "prop_type": "strikeouts_pitcher",
    "pick": "UNDER 8.5",
    "projected": 5.33,
    "model_prob": 0.908,
    "fair_prob": 0.48,
    "odds": -105,
    "value_edge": 0.893,
    "kelly_fraction": 0.25,
    "confidence": "HIGH",
    "generated_at": "2026-05-31"
  },
  {
    "player": "Freddie Freeman",
    "team": "Los Angeles Dodgers",
    "opponent": "Philadelphia Phillies",
    "prop_type": "hits",
    "pick": "UNDER 1.5",
    "projected": 0.93,
    "model_prob": 0.762,
    "fair_prob": 0.448,
    "odds": 110,
    "value_edge": 0.702,
    "kelly_fraction": 0.25,
    "confidence": "HIGH",
    "generated_at": "2026-05-31"
  },
  {
    "player": "Will Smith",
    "team": "Los Angeles Dodgers",
    "opponent": "Philadelphia Phillies",
    "prop_type": "hits",
    "pick": "UNDER 1.5",
    "projected": 0.82,
    "model_prob": 0.801,
    "fair_prob": 0.472,
    "odds": 105,
    "value_edge": 0.697,
    "kelly_fraction": 0.25,
    "confidence": "HIGH",
    "generated_at": "2026-05-31"
  },
  {
    "player": "Alec Bohm",
    "team": "Philadelphia Phillies",
    "opponent": "Los Angeles Dodgers",
    "prop_type": "hits",
    "pick": "UNDER 1.5",
    "projected": 0.9,
    "model_prob": 0.771,
    "fair_prob": 0.459,
    "odds": 105,
    "value_edge": 0.679,
    "kelly_fraction": 0.25,
    "confidence": "HIGH",
    "generated_at": "2026-05-31"
  },
  {
    "player": "Dominic Canzone",
    "team": "Seattle Mariners",
    "opponent": "Arizona Diamondbacks",
    "prop_type": "hits",
    "pick": "UNDER 1.5",
    "projected": 0.5,
    "model_prob": 0.909,
    "fair_prob": 0.552,
    "odds": -142,
    "value_edge": 0.646,
    "kelly_fraction": 0.25,
    "confidence": "HIGH",
    "generated_at": "2026-05-31"
  },
  {
    "player": "Alex Call",
    "team": "Los Angeles Dodgers",
    "opponent": "Philadelphia Phillies",
    "prop_type": "hits",
    "pick": "UNDER 1.5",
    "projected": 0.52,
    "model_prob": 0.905,
    "fair_prob": 0.552,
    "odds": -142,
    "value_edge": 0.639,
    "kelly_fraction": 0.25,
    "confidence": "HIGH",
    "generated_at": "2026-05-31"
  },
  {
    "player": "Tommy Troy",
    "team": "Arizona Diamondbacks",
    "opponent": "Seattle Mariners",
    "prop_type": "hits",
    "pick": "OVER 0.5",
    "projected": 0.83,
    "model_prob": 0.565,
    "fair_prob": 0.349,
    "odds": 170,
    "value_edge": 0.622,
    "kelly_fraction": 0.25,
    "confidence": "MEDIUM",
    "generated_at": "2026-05-31"
  },
  {
    "player": "Ryan Waldschmidt",
    "team": "Arizona Diamondbacks",
    "opponent": "Seattle Mariners",
    "prop_type": "hits",
    "pick": "OVER 0.5",
    "projected": 0.98,
    "model_prob": 0.625,
    "fair_prob": 0.392,
    "odds": 140,
    "value_edge": 0.593,
    "kelly_fraction": 0.25,
    "confidence": "HIGH",
    "generated_at": "2026-05-31"
  },
  {
    "player": "Tyler Soderstrom",
    "team": "Athletics",
    "opponent": "New York Yankees",
    "prop_type": "hits",
    "pick": "UNDER 1.5",
    "projected": 0.88,
    "model_prob": 0.78,
    "fair_prob": 0.495,
    "odds": -110,
    "value_edge": 0.576,
    "kelly_fraction": 0.25,
    "confidence": "HIGH",
    "generated_at": "2026-05-31"
  },
  {
    "player": "Austin Wells",
    "team": "New York Yankees",
    "opponent": "Athletics",
    "prop_type": "hits",
    "pick": "UNDER 1.5",
    "projected": 0.54,
    "model_prob": 0.896,
    "fair_prob": 0.583,
    "odds": -162,
    "value_edge": 0.538,
    "kelly_fraction": 0.25,
    "confidence": "HIGH",
    "generated_at": "2026-05-31"
  },
  {
    "player": "Paul Goldschmidt",
    "team": "New York Yankees",
    "opponent": "Athletics",
    "prop_type": "hits",
    "pick": "UNDER 1.5",
    "projected": 0.94,
    "model_prob": 0.758,
    "fair_prob": 0.495,
    "odds": -110,
    "value_edge": 0.532,
    "kelly_fraction": 0.25,
    "confidence": "HIGH",
    "generated_at": "2026-05-31"
  },
  {
    "player": "Colt Emerson",
    "team": "Seattle Mariners",
    "opponent": "Arizona Diamondbacks",
    "prop_type": "hits",
    "pick": "UNDER 1.5",
    "projected": 0.75,
    "model_prob": 0.827,
    "fair_prob": 0.541,
    "odds": -135,
    "value_edge": 0.529,
    "kelly_fraction": 0.25,
    "confidence": "HIGH",
    "generated_at": "2026-05-31"
  },
  {
    "player": "Casey Schmitt",
    "team": "San Francisco Giants",
    "opponent": "Colorado Rockies",
    "prop_type": "hits",
    "pick": "OVER 0.5",
    "projected": 1.11,
    "model_prob": 0.671,
    "fair_prob": 0.448,
    "odds": 110,
    "value_edge": 0.498,
    "kelly_fraction": 0.25,
    "confidence": "HIGH",
    "generated_at": "2026-05-31"
  },
  {
    "player": "Willi Castro",
    "team": "Colorado Rockies",
    "opponent": "San Francisco Giants",
    "prop_type": "hits",
    "pick": "UNDER 2.5",
    "projected": 1.0,
    "model_prob": 0.92,
    "fair_prob": 0.615,
    "odds": -188,
    "value_edge": 0.495,
    "kelly_fraction": 0.25,
    "confidence": "HIGH",
    "generated_at": "2026-05-31"
  },
  {
    "player": "Corbin Carroll",
    "team": "Arizona Diamondbacks",
    "opponent": "Seattle Mariners",
    "prop_type": "hits",
    "pick": "OVER 0.5",
    "projected": 1.26,
    "model_prob": 0.717,
    "fair_prob": 0.48,
    "odds": -105,
    "value_edge": 0.495,
    "kelly_fraction": 0.25,
    "confidence": "HIGH",
    "generated_at": "2026-05-31"
  },
  {
    "player": "Luke Raley",
    "team": "Seattle Mariners",
    "opponent": "Arizona Diamondbacks",
    "prop_type": "hits",
    "pick": "UNDER 1.5",
    "projected": 0.78,
    "model_prob": 0.815,
    "fair_prob": 0.558,
    "odds": -135,
    "value_edge": 0.46,
    "kelly_fraction": 0.25,
    "confidence": "HIGH",
    "generated_at": "2026-05-31"
  },
  {
    "player": "Rafael Devers",
    "team": "San Francisco Giants",
    "opponent": "Colorado Rockies",
    "prop_type": "hits",
    "pick": "OVER 0.5",
    "projected": 0.93,
    "model_prob": 0.606,
    "fair_prob": 0.417,
    "odds": 130,
    "value_edge": 0.454,
    "kelly_fraction": 0.25,
    "confidence": "HIGH",
    "generated_at": "2026-05-31"
  },
  {
    "player": "Shohei Ohtani",
    "team": "Los Angeles Dodgers",
    "opponent": "Philadelphia Phillies",
    "prop_type": "hits",
    "pick": "OVER 0.5",
    "projected": 1.23,
    "model_prob": 0.707,
    "fair_prob": 0.49,
    "odds": -110,
    "value_edge": 0.442,
    "kelly_fraction": 0.25,
    "confidence": "HIGH",
    "generated_at": "2026-05-31"
  },
  {
    "player": "Justin Crawford",
    "team": "Philadelphia Phillies",
    "opponent": "Los Angeles Dodgers",
    "prop_type": "hits",
    "pick": "UNDER 0.5",
    "projected": 0.48,
    "model_prob": 0.616,
    "fair_prob": 0.428,
    "odds": 120,
    "value_edge": 0.438,
    "kelly_fraction": 0.25,
    "confidence": "HIGH",
    "generated_at": "2026-05-31"
  },
  {
    "player": "Shea Langeliers",
    "team": "Athletics",
    "opponent": "New York Yankees",
    "prop_type": "hits",
    "pick": "UNDER 1.5",
    "projected": 0.92,
    "model_prob": 0.767,
    "fair_prob": 0.547,
    "odds": -135,
    "value_edge": 0.402,
    "kelly_fraction": 0.25,
    "confidence": "HIGH",
    "generated_at": "2026-05-31"
  },
  {
    "player": "Ketel Marte",
    "team": "Arizona Diamondbacks",
    "opponent": "Seattle Mariners",
    "prop_type": "hits",
    "pick": "OVER 0.5",
    "projected": 1.47,
    "model_prob": 0.77,
    "fair_prob": 0.552,
    "odds": -142,
    "value_edge": 0.395,
    "kelly_fraction": 0.25,
    "confidence": "HIGH",
    "generated_at": "2026-05-31"
  },
  {
    "player": "Trent Grisham",
    "team": "New York Yankees",
    "opponent": "Athletics",
    "prop_type": "hits",
    "pick": "OVER 0.5",
    "projected": 0.87,
    "model_prob": 0.582,
    "fair_prob": 0.417,
    "odds": 126,
    "value_edge": 0.394,
    "kelly_fraction": 0.2496,
    "confidence": "HIGH",
    "generated_at": "2026-05-31"
  },
  {
    "player": "Gabriel Moreno",
    "team": "Arizona Diamondbacks",
    "opponent": "Seattle Mariners",
    "prop_type": "hits",
    "pick": "OVER 0.5",
    "projected": 0.99,
    "model_prob": 0.63,
    "fair_prob": 0.463,
    "odds": 105,
    "value_edge": 0.359,
    "kelly_fraction": 0.25,
    "confidence": "HIGH",
    "generated_at": "2026-05-31"
  },
  {
    "player": "Jake McCarthy",
    "team": "Colorado Rockies",
    "opponent": "San Francisco Giants",
    "prop_type": "hits",
    "pick": "UNDER 2.5",
    "projected": 0.97,
    "model_prob": 0.926,
    "fair_prob": 0.686,
    "odds": -270,
    "value_edge": 0.349,
    "kelly_fraction": 0.25,
    "confidence": "HIGH",
    "generated_at": "2026-05-31"
  },
  {
    "player": "J.P. Crawford",
    "team": "Seattle Mariners",
    "opponent": "Arizona Diamondbacks",
    "prop_type": "hits",
    "pick": "UNDER 1.5",
    "projected": 0.91,
    "model_prob": 0.768,
    "fair_prob": 0.572,
    "odds": -154,
    "value_edge": 0.344,
    "kelly_fraction": 0.25,
    "confidence": "HIGH",
    "generated_at": "2026-05-31"
  },
  {
    "player": "Andy Pages",
    "team": "Los Angeles Dodgers",
    "opponent": "Philadelphia Phillies",
    "prop_type": "hits",
    "pick": "OVER 0.5",
    "projected": 0.99,
    "model_prob": 0.63,
    "fair_prob": 0.469,
    "odds": 100,
    "value_edge": 0.342,
    "kelly_fraction": 0.25,
    "confidence": "HIGH",
    "generated_at": "2026-05-31"
  },
  {
    "player": "Santiago Espinal",
    "team": "Los Angeles Dodgers",
    "opponent": "Philadelphia Phillies",
    "prop_type": "hits",
    "pick": "UNDER 0.5",
    "projected": 0.29,
    "model_prob": 0.746,
    "fair_prob": 0.562,
    "odds": -148,
    "value_edge": 0.327,
    "kelly_fraction": 0.25,
    "confidence": "HIGH",
    "generated_at": "2026-05-31"
  },
  {
    "player": "Edouard Julien",
    "team": "Colorado Rockies",
    "opponent": "San Francisco Giants",
    "prop_type": "hits",
    "pick": "UNDER 1.5",
    "projected": 0.36,
    "model_prob": 0.948,
    "fair_prob": 0.723,
    "odds": -330,
    "value_edge": 0.312,
    "kelly_fraction": 0.25,
    "confidence": "HIGH",
    "generated_at": "2026-05-31"
  },
  {
    "player": "Geraldo Perdomo",
    "team": "Arizona Diamondbacks",
    "opponent": "Seattle Mariners",
    "prop_type": "hits",
    "pick": "OVER 0.5",
    "projected": 0.88,
    "model_prob": 0.585,
    "fair_prob": 0.448,
    "odds": 110,
    "value_edge": 0.305,
    "kelly_fraction": 0.207,
    "confidence": "HIGH",
    "generated_at": "2026-05-31"
  },
  {
    "player": "Kyle Schwarber",
    "team": "Philadelphia Phillies",
    "opponent": "Los Angeles Dodgers",
    "prop_type": "hits",
    "pick": "OVER 0.5",
    "projected": 1.04,
    "model_prob": 0.645,
    "fair_prob": 0.495,
    "odds": -110,
    "value_edge": 0.304,
    "kelly_fraction": 0.25,
    "confidence": "HIGH",
    "generated_at": "2026-05-31"
  },
  {
    "player": "Ildemaro Vargas",
    "team": "Arizona Diamondbacks",
    "opponent": "Seattle Mariners",
    "prop_type": "hits",
    "pick": "OVER 0.5",
    "projected": 0.9,
    "model_prob": 0.592,
    "fair_prob": 0.459,
    "odds": 105,
    "value_edge": 0.289,
    "kelly_fraction": 0.203,
    "confidence": "HIGH",
    "generated_at": "2026-05-31"
  },
  {
    "player": "Nick Kurtz",
    "team": "Athletics",
    "opponent": "New York Yankees",
    "prop_type": "hits",
    "pick": "UNDER 1.5",
    "projected": 0.95,
    "model_prob": 0.753,
    "fair_prob": 0.59,
    "odds": -168,
    "value_edge": 0.275,
    "kelly_fraction": 0.25,
    "confidence": "HIGH",
    "generated_at": "2026-05-31"
  },
  {
    "player": "Jazz Chisholm Jr.",
    "team": "New York Yankees",
    "opponent": "Athletics",
    "prop_type": "hits",
    "pick": "OVER 0.5",
    "projected": 1.06,
    "model_prob": 0.655,
    "fair_prob": 0.516,
    "odds": -120,
    "value_edge": 0.269,
    "kelly_fraction": 0.24,
    "confidence": "HIGH",
    "generated_at": "2026-05-31"
  },
  {
    "player": "Randy Arozarena",
    "team": "Seattle Mariners",
    "opponent": "Arizona Diamondbacks",
    "prop_type": "hits",
    "pick": "OVER 0.5",
    "projected": 0.99,
    "model_prob": 0.627,
    "fair_prob": 0.5,
    "odds": -115,
    "value_edge": 0.255,
    "kelly_fraction": 0.1988,
    "confidence": "HIGH",
    "generated_at": "2026-05-31"
  },
  {
    "player": "Roki Sasaki",
    "team": "Los Angeles Dodgers",
    "opponent": "Philadelphia Phillies",
    "prop_type": "strikeouts_pitcher",
    "pick": "UNDER 5.5",
    "projected": 4.6,
    "model_prob": 0.686,
    "fair_prob": 0.552,
    "odds": -142,
    "value_edge": 0.242,
    "kelly_fraction": 0.2395,
    "confidence": "HIGH",
    "generated_at": "2026-05-31"
  },
  {
    "player": "Ezequiel Tovar",
    "team": "Colorado Rockies",
    "opponent": "San Francisco Giants",
    "prop_type": "hits",
    "pick": "UNDER 1.5",
    "projected": 0.9,
    "model_prob": 0.772,
    "fair_prob": 0.624,
    "odds": -198,
    "value_edge": 0.237,
    "kelly_fraction": 0.25,
    "confidence": "HIGH",
    "generated_at": "2026-05-31"
  },
  {
    "player": "Ben Rice",
    "team": "New York Yankees",
    "opponent": "Athletics",
    "prop_type": "hits",
    "pick": "UNDER 1.5",
    "projected": 1.16,
    "model_prob": 0.678,
    "fair_prob": 0.551,
    "odds": -140,
    "value_edge": 0.231,
    "kelly_fraction": 0.2271,
    "confidence": "HIGH",
    "generated_at": "2026-05-31"
  },
  {
    "player": "Troy Johnston",
    "team": "Colorado Rockies",
    "opponent": "San Francisco Giants",
    "prop_type": "hits",
    "pick": "UNDER 1.5",
    "projected": 0.97,
    "model_prob": 0.748,
    "fair_prob": 0.608,
    "odds": -182,
    "value_edge": 0.23,
    "kelly_fraction": 0.25,
    "confidence": "HIGH",
    "generated_at": "2026-05-31"
  },
  {
    "player": "Brett Sullivan",
    "team": "Colorado Rockies",
    "opponent": "San Francisco Giants",
    "prop_type": "hits",
    "pick": "UNDER 1.5",
    "projected": 0.58,
    "model_prob": 0.884,
    "fair_prob": 0.723,
    "odds": -330,
    "value_edge": 0.223,
    "kelly_fraction": 0.25,
    "confidence": "HIGH",
    "generated_at": "2026-05-31"
  },
  {
    "player": "Matt Chapman",
    "team": "San Francisco Giants",
    "opponent": "Colorado Rockies",
    "prop_type": "hits",
    "pick": "UNDER 1.5",
    "projected": 0.86,
    "model_prob": 0.786,
    "fair_prob": 0.67,
    "odds": -248,
    "value_edge": 0.173,
    "kelly_fraction": 0.25,
    "confidence": "HIGH",
    "generated_at": "2026-05-31"
  },
  {
    "player": "Miguel Rojas",
    "team": "Los Angeles Dodgers",
    "opponent": "Philadelphia Phillies",
    "prop_type": "hits",
    "pick": "UNDER 0.5",
    "projected": 0.52,
    "model_prob": 0.592,
    "fair_prob": 0.51,
    "odds": -120,
    "value_edge": 0.16,
    "kelly_fraction": 0.1021,
    "confidence": "HIGH",
    "generated_at": "2026-05-31"
  },
  {
    "player": "Henry Bolte",
    "team": "Athletics",
    "opponent": "New York Yankees",
    "prop_type": "hits",
    "pick": "OVER 0.5",
    "projected": 0.9,
    "model_prob": 0.591,
    "fair_prob": 0.51,
    "odds": -120,
    "value_edge": 0.159,
    "kelly_fraction": 0.1011,
    "confidence": "MEDIUM",
    "generated_at": "2026-05-31"
  },
  {
    "player": "George Springer",
    "team": "Toronto Blue Jays",
    "opponent": "Baltimore Orioles",
    "prop_type": "hits",
    "pick": "UNDER 1.5",
    "projected": 0.89,
    "model_prob": 0.776,
    "fair_prob": 0.674,
    "odds": -254,
    "value_edge": 0.152,
    "kelly_fraction": 0.2075,
    "confidence": "HIGH",
    "generated_at": "2026-05-31"
  },
  {
    "player": "Zack Gelof",
    "team": "Athletics",
    "opponent": "New York Yankees",
    "prop_type": "hits",
    "pick": "OVER 0.5",
    "projected": 0.83,
    "model_prob": 0.566,
    "fair_prob": 0.5,
    "odds": -115,
    "value_edge": 0.132,
    "kelly_fraction": 0.0665,
    "confidence": "HIGH",
    "generated_at": "2026-05-31"
  },
  {
    "player": "Vladimir Guerrero Jr.",
    "team": "Toronto Blue Jays",
    "opponent": "Baltimore Orioles",
    "prop_type": "hits",
    "pick": "UNDER 1.5",
    "projected": 1.08,
    "model_prob": 0.708,
    "fair_prob": 0.638,
    "odds": -214,
    "value_edge": 0.109,
    "kelly_fraction": 0.0836,
    "confidence": "HIGH",
    "generated_at": "2026-05-31"
  },
  {
    "player": "Brandon Marsh",
    "team": "Philadelphia Phillies",
    "opponent": "Los Angeles Dodgers",
    "prop_type": "hits",
    "pick": "OVER 0.5",
    "projected": 0.93,
    "model_prob": 0.607,
    "fair_prob": 0.549,
    "odds": -130,
    "value_edge": 0.106,
    "kelly_fraction": 0.0951,
    "confidence": "HIGH",
    "generated_at": "2026-05-31"
  },
  {
    "player": "Jung Hoo Lee",
    "team": "San Francisco Giants",
    "opponent": "Colorado Rockies",
    "prop_type": "hits",
    "pick": "UNDER 1.5",
    "projected": 1.18,
    "model_prob": 0.668,
    "fair_prob": 0.608,
    "odds": -182,
    "value_edge": 0.1,
    "kelly_fraction": 0.0649,
    "confidence": "HIGH",
    "generated_at": "2026-05-31"
  },
  {
    "player": "Eric Haase",
    "team": "San Francisco Giants",
    "opponent": "Colorado Rockies",
    "prop_type": "hits",
    "pick": "UNDER 1.5",
    "projected": 0.75,
    "model_prob": 0.827,
    "fair_prob": 0.759,
    "odds": -420,
    "value_edge": 0.089,
    "kelly_fraction": 0.0985,
    "confidence": "MEDIUM",
    "generated_at": "2026-05-31"
  },
  {
    "player": "Hunter Goodman",
    "team": "Colorado Rockies",
    "opponent": "San Francisco Giants",
    "prop_type": "hits",
    "pick": "UNDER 1.5",
    "projected": 0.89,
    "model_prob": 0.776,
    "fair_prob": 0.723,
    "odds": -330,
    "value_edge": 0.074,
    "kelly_fraction": 0.0377,
    "confidence": "HIGH",
    "generated_at": "2026-05-31"
  },
  {
    "player": "TJ Rumfield",
    "team": "Colorado Rockies",
    "opponent": "San Francisco Giants",
    "prop_type": "hits",
    "pick": "UNDER 1.5",
    "projected": 0.91,
    "model_prob": 0.768,
    "fair_prob": 0.723,
    "odds": -330,
    "value_edge": 0.062,
    "kelly_fraction": 0.0012,
    "confidence": "HIGH",
    "generated_at": "2026-05-31"
  },
  {
    "player": "Ryan McMahon",
    "team": "New York Yankees",
    "opponent": "Athletics",
    "prop_type": "hits",
    "pick": "UNDER 0.5",
    "projected": 0.5,
    "model_prob": 0.607,
    "fair_prob": 0.572,
    "odds": -154,
    "value_edge": 0.062,
    "kelly_fraction": 0.0023,
    "confidence": "MEDIUM",
    "generated_at": "2026-05-31"
  }
]