{
  "summary": {
    "total": 78,
    "hits": 37,
    "misses": 41,
    "hit_rate": 47.4
  },
  "by_prop": {
    "hits": {
      "hits": 28,
      "total": 60,
      "hit_rate": 46.7
    },
    "strikeouts_pitcher": {
      "hits": 9,
      "total": 18,
      "hit_rate": 50.0
    }
  },
  "by_confidence": {
    "HIGH": {
      "hits": 32,
      "total": 68,
      "hit_rate": 47.1
    },
    "MEDIUM": {
      "hits": 4,
      "total": 8,
      "hit_rate": 50.0
    },
    "LOW": {
      "hits": 1,
      "total": 2,
      "hit_rate": 50.0
    }
  },
  "results": [
    {
      "date": "2026-06-04",
      "player": "Travis Bazzana",
      "team": "Cleveland Guardians",
      "prop_type": "hits",
      "pick": "OVER 0.5",
      "projected": 1.0,
      "actual": 0.0,
      "result": "miss",
      "confidence": "HIGH",
      "value_edge": 1.623
    },
    {
      "date": "2026-06-04",
      "player": "Zack Gelof",
      "team": "Athletics",
      "prop_type": "hits",
      "pick": "OVER 0.5",
      "projected": 1.02,
      "actual": 1.0,
      "result": "hit",
      "confidence": "HIGH",
      "value_edge": 1.114
    },
    {
      "date": "2026-06-04",
      "player": "Jazz Chisholm Jr.",
      "team": "New York Yankees",
      "prop_type": "hits",
      "pick": "OVER 0.5",
      "projected": 1.03,
      "actual": 0.0,
      "result": "miss",
      "confidence": "HIGH",
      "value_edge": 0.882
    },
    {
      "date": "2026-06-04",
      "player": "Brayan Rocchio",
      "team": "Cleveland Guardians",
      "prop_type": "hits",
      "pick": "OVER 0.5",
      "projected": 0.89,
      "actual": 0.0,
      "result": "miss",
      "confidence": "HIGH",
      "value_edge": 0.848
    },
    {
      "date": "2026-06-04",
      "player": "Shota Imanaga",
      "team": "Chicago Cubs",
      "prop_type": "strikeouts_pitcher",
      "pick": "UNDER 7.5",
      "projected": 5.75,
      "actual": 5.0,
      "result": "hit",
      "confidence": "HIGH",
      "value_edge": 0.79
    },
    {
      "date": "2026-06-04",
      "player": "Rafael Devers",
      "team": "San Francisco Giants",
      "prop_type": "hits",
      "pick": "OVER 0.5",
      "projected": 0.93,
      "actual": 1.0,
      "result": "hit",
      "confidence": "HIGH",
      "value_edge": 0.609
    },
    {
      "date": "2026-06-04",
      "player": "Michael Harris II",
      "team": "Atlanta Braves",
      "prop_type": "hits",
      "pick": "OVER 0.5",
      "projected": 1.23,
      "actual": 1.0,
      "result": "hit",
      "confidence": "HIGH",
      "value_edge": 0.415
    },
    {
      "date": "2026-06-04",
      "player": "Ernie Clement",
      "team": "Toronto Blue Jays",
      "prop_type": "hits",
      "pick": "OVER 0.5",
      "projected": 1.27,
      "actual": 3.0,
      "result": "hit",
      "confidence": "HIGH",
      "value_edge": 0.375
    },
    {
      "date": "2026-06-04",
      "player": "Gabriel Moreno",
      "team": "Arizona Diamondbacks",
      "prop_type": "hits",
      "pick": "OVER 0.5",
      "projected": 1.03,
      "actual": 0.0,
      "result": "miss",
      "confidence": "HIGH",
      "value_edge": 0.329
    },
    {
      "date": "2026-06-04",
      "player": "Christian Yelich",
      "team": "Milwaukee Brewers",
      "prop_type": "hits",
      "pick": "OVER 0.5",
      "projected": 1.05,
      "actual": 2.0,
      "result": "hit",
      "confidence": "HIGH",
      "value_edge": 0.302
    },
    {
      "date": "2026-06-04",
      "player": "William Contreras",
      "team": "Milwaukee Brewers",
      "prop_type": "hits",
      "pick": "OVER 0.5",
      "projected": 1.17,
      "actual": 0.0,
      "result": "miss",
      "confidence": "HIGH",
      "value_edge": 0.275
    },
    {
      "date": "2026-06-04",
      "player": "Ryne Nelson",
      "team": "Arizona Diamondbacks",
      "prop_type": "strikeouts_pitcher",
      "pick": "OVER 3.5",
      "projected": 4.33,
      "actual": 3.0,
      "result": "miss",
      "confidence": "HIGH",
      "value_edge": 0.263
    },
    {
      "date": "2026-06-04",
      "player": "Charles McAdoo",
      "team": "Toronto Blue Jays",
      "prop_type": "hits",
      "pick": "OVER 0.5",
      "projected": 1.0,
      "actual": 1.0,
      "result": "hit",
      "confidence": "HIGH",
      "value_edge": 0.216
    },
    {
      "date": "2026-06-04",
      "player": "Vinnie Pasquantino",
      "team": "Kansas City Royals",
      "prop_type": "hits",
      "pick": "OVER 0.5",
      "projected": 0.88,
      "actual": 0.0,
      "result": "miss",
      "confidence": "HIGH",
      "value_edge": 0.213
    },
    {
      "date": "2026-06-04",
      "player": "Taylor Trammell",
      "team": "Houston Astros",
      "prop_type": "hits",
      "pick": "OVER 0.5",
      "projected": 0.92,
      "actual": 2.0,
      "result": "hit",
      "confidence": "MEDIUM",
      "value_edge": 0.199
    },
    {
      "date": "2026-06-04",
      "player": "Salvador Perez",
      "team": "Kansas City Royals",
      "prop_type": "hits",
      "pick": "OVER 0.5",
      "projected": 0.84,
      "actual": 1.0,
      "result": "hit",
      "confidence": "HIGH",
      "value_edge": 0.19
    },
    {
      "date": "2026-06-04",
      "player": "Oneil Cruz",
      "team": "Pittsburgh Pirates",
      "prop_type": "hits",
      "pick": "OVER 0.5",
      "projected": 1.03,
      "actual": 2.0,
      "result": "hit",
      "confidence": "HIGH",
      "value_edge": 0.166
    },
    {
      "date": "2026-06-04",
      "player": "Jared Jones",
      "team": "Pittsburgh Pirates",
      "prop_type": "strikeouts_pitcher",
      "pick": "OVER 5.5",
      "projected": 6.0,
      "actual": 4.0,
      "result": "miss",
      "confidence": "MEDIUM",
      "value_edge": 0.141
    },
    {
      "date": "2026-06-04",
      "player": "Justin Wrobleski",
      "team": "Los Angeles Dodgers",
      "prop_type": "strikeouts_pitcher",
      "pick": "OVER 3.5",
      "projected": 4.18,
      "actual": 4.0,
      "result": "hit",
      "confidence": "MEDIUM",
      "value_edge": 0.114
    },
    {
      "date": "2026-06-04",
      "player": "Seth Lugo",
      "team": "Kansas City Royals",
      "prop_type": "strikeouts_pitcher",
      "pick": "OVER 4.5",
      "projected": 5.0,
      "actual": 4.0,
      "result": "miss",
      "confidence": "LOW",
      "value_edge": 0.06
    },
    {
      "date": "2026-06-03",
      "player": "Freddy Peralta",
      "team": "New York Mets",
      "prop_type": "strikeouts_pitcher",
      "pick": "UNDER 6.5",
      "projected": 5.38,
      "actual": 6.0,
      "result": "hit",
      "confidence": "HIGH",
      "value_edge": 0.437
    },
    {
      "date": "2026-06-03",
      "player": "Michael Lorenzen",
      "team": "Colorado Rockies",
      "prop_type": "strikeouts_pitcher",
      "pick": "UNDER 4.5",
      "projected": 3.42,
      "actual": 5.0,
      "result": "miss",
      "confidence": "HIGH",
      "value_edge": 0.436
    },
    {
      "date": "2026-06-03",
      "player": "Taylor Trammell",
      "team": "Houston Astros",
      "prop_type": "hits",
      "pick": "OVER 0.5",
      "projected": 0.94,
      "actual": 0.0,
      "result": "miss",
      "confidence": "MEDIUM",
      "value_edge": 0.341
    },
    {
      "date": "2026-06-03",
      "player": "Sal Stewart",
      "team": "Cincinnati Reds",
      "prop_type": "hits",
      "pick": "OVER 0.5",
      "projected": 1.07,
      "actual": 1.0,
      "result": "hit",
      "confidence": "HIGH",
      "value_edge": 0.334
    },
    {
      "date": "2026-06-03",
      "player": "Ceddanne Rafaela",
      "team": "Boston Red Sox",
      "prop_type": "hits",
      "pick": "OVER 0.5",
      "projected": 1.07,
      "actual": 3.0,
      "result": "hit",
      "confidence": "HIGH",
      "value_edge": 0.314
    },
    {
      "date": "2026-06-03",
      "player": "Shohei Ohtani",
      "team": "Los Angeles Dodgers",
      "prop_type": "strikeouts_pitcher",
      "pick": "OVER 5.5",
      "projected": 6.78,
      "actual": 6.0,
      "result": "hit",
      "confidence": "HIGH",
      "value_edge": 0.313
    },
    {
      "date": "2026-06-03",
      "player": "Wilyer Abreu",
      "team": "Boston Red Sox",
      "prop_type": "hits",
      "pick": "OVER 0.5",
      "projected": 0.99,
      "actual": 2.0,
      "result": "hit",
      "confidence": "HIGH",
      "value_edge": 0.258
    },
    {
      "date": "2026-06-03",
      "player": "Stephen Kolek",
      "team": "Kansas City Royals",
      "prop_type": "strikeouts_pitcher",
      "pick": "UNDER 4.5",
      "projected": 3.8,
      "actual": 8.0,
      "result": "miss",
      "confidence": "HIGH",
      "value_edge": 0.231
    },
    {
      "date": "2026-06-03",
      "player": "Brayan Rocchio",
      "team": "Cleveland Guardians",
      "prop_type": "hits",
      "pick": "OVER 0.5",
      "projected": 1.06,
      "actual": 0.0,
      "result": "miss",
      "confidence": "HIGH",
      "value_edge": 0.217
    },
    {
      "date": "2026-06-03",
      "player": "Randy Arozarena",
      "team": "Seattle Mariners",
      "prop_type": "hits",
      "pick": "OVER 0.5",
      "projected": 0.93,
      "actual": 0.0,
      "result": "miss",
      "confidence": "HIGH",
      "value_edge": 0.213
    },
    {
      "date": "2026-06-03",
      "player": "Jazz Chisholm Jr.",
      "team": "New York Yankees",
      "prop_type": "hits",
      "pick": "OVER 0.5",
      "projected": 1.15,
      "actual": 1.0,
      "result": "hit",
      "confidence": "HIGH",
      "value_edge": 0.205
    },
    {
      "date": "2026-06-03",
      "player": "Corbin Carroll",
      "team": "Arizona Diamondbacks",
      "prop_type": "hits",
      "pick": "OVER 0.5",
      "projected": 1.27,
      "actual": 0.0,
      "result": "miss",
      "confidence": "HIGH",
      "value_edge": 0.199
    },
    {
      "date": "2026-06-03",
      "player": "Mookie Betts",
      "team": "Los Angeles Dodgers",
      "prop_type": "hits",
      "pick": "OVER 0.5",
      "projected": 0.87,
      "actual": 0.0,
      "result": "miss",
      "confidence": "HIGH",
      "value_edge": 0.188
    },
    {
      "date": "2026-06-03",
      "player": "Jung Hoo Lee",
      "team": "San Francisco Giants",
      "prop_type": "hits",
      "pick": "OVER 0.5",
      "projected": 1.42,
      "actual": 2.0,
      "result": "hit",
      "confidence": "HIGH",
      "value_edge": 0.183
    },
    {
      "date": "2026-06-03",
      "player": "Travis Bazzana",
      "team": "Cleveland Guardians",
      "prop_type": "hits",
      "pick": "OVER 0.5",
      "projected": 1.23,
      "actual": 0.0,
      "result": "miss",
      "confidence": "HIGH",
      "value_edge": 0.155
    },
    {
      "date": "2026-06-03",
      "player": "Bryce Eldridge",
      "team": "San Francisco Giants",
      "prop_type": "hits",
      "pick": "OVER 0.5",
      "projected": 0.88,
      "actual": 1.0,
      "result": "hit",
      "confidence": "HIGH",
      "value_edge": 0.147
    },
    {
      "date": "2026-06-03",
      "player": "Paul Skenes",
      "team": "Pittsburgh Pirates",
      "prop_type": "strikeouts_pitcher",
      "pick": "UNDER 6.5",
      "projected": 6.25,
      "actual": 7.0,
      "result": "miss",
      "confidence": "MEDIUM",
      "value_edge": 0.138
    },
    {
      "date": "2026-06-03",
      "player": "Willi Castro",
      "team": "Colorado Rockies",
      "prop_type": "hits",
      "pick": "OVER 0.5",
      "projected": 1.07,
      "actual": 0.0,
      "result": "miss",
      "confidence": "HIGH",
      "value_edge": 0.135
    },
    {
      "date": "2026-06-03",
      "player": "Troy Johnston",
      "team": "Colorado Rockies",
      "prop_type": "hits",
      "pick": "OVER 0.5",
      "projected": 1.19,
      "actual": 2.0,
      "result": "hit",
      "confidence": "HIGH",
      "value_edge": 0.134
    },
    {
      "date": "2026-06-03",
      "player": "Spencer Arrighetti",
      "team": "Houston Astros",
      "prop_type": "strikeouts_pitcher",
      "pick": "UNDER 5.5",
      "projected": 5.38,
      "actual": 3.0,
      "result": "hit",
      "confidence": "MEDIUM",
      "value_edge": 0.128
    },
    {
      "date": "2026-06-03",
      "player": "Fernando Tatis Jr.",
      "team": "San Diego Padres",
      "prop_type": "hits",
      "pick": "OVER 0.5",
      "projected": 1.29,
      "actual": 1.0,
      "result": "hit",
      "confidence": "HIGH",
      "value_edge": 0.124
    },
    {
      "date": "2026-06-03",
      "player": "Zack Gelof",
      "team": "Athletics",
      "prop_type": "hits",
      "pick": "OVER 0.5",
      "projected": 1.02,
      "actual": 1.0,
      "result": "hit",
      "confidence": "HIGH",
      "value_edge": 0.109
    },
    {
      "date": "2026-06-03",
      "player": "Josh Naylor",
      "team": "Seattle Mariners",
      "prop_type": "hits",
      "pick": "OVER 0.5",
      "projected": 0.99,
      "actual": 0.0,
      "result": "miss",
      "confidence": "HIGH",
      "value_edge": 0.102
    },
    {
      "date": "2026-06-03",
      "player": "Casey Schmitt",
      "team": "San Francisco Giants",
      "prop_type": "hits",
      "pick": "OVER 0.5",
      "projected": 1.12,
      "actual": 1.0,
      "result": "hit",
      "confidence": "HIGH",
      "value_edge": 0.101
    },
    {
      "date": "2026-06-03",
      "player": "Daulton Varsho",
      "team": "Toronto Blue Jays",
      "prop_type": "hits",
      "pick": "OVER 0.5",
      "projected": 0.97,
      "actual": 1.0,
      "result": "hit",
      "confidence": "MEDIUM",
      "value_edge": 0.077
    },
    {
      "date": "2026-06-03",
      "player": "Nathan Lukes",
      "team": "Toronto Blue Jays",
      "prop_type": "hits",
      "pick": "OVER 0.5",
      "projected": 1.24,
      "actual": 2.0,
      "result": "hit",
      "confidence": "HIGH",
      "value_edge": 0.069
    },
    {
      "date": "2026-06-03",
      "player": "Andre Pallante",
      "team": "St. Louis Cardinals",
      "prop_type": "strikeouts_pitcher",
      "pick": "OVER 3.5",
      "projected": 4.18,
      "actual": 5.0,
      "result": "hit",
      "confidence": "LOW",
      "value_edge": 0.061
    },
    {
      "date": "2026-06-03",
      "player": "Alec Burleson",
      "team": "St. Louis Cardinals",
      "prop_type": "hits",
      "pick": "OVER 0.5",
      "projected": 1.12,
      "actual": 2.0,
      "result": "hit",
      "confidence": "HIGH",
      "value_edge": 0.051
    },
    {
      "date": "2026-06-02",
      "player": "Jahmai Jones",
      "team": "Detroit Tigers",
      "prop_type": "hits",
      "pick": "UNDER 0.5",
      "projected": 0.18,
      "actual": 0.0,
      "result": "hit",
      "confidence": "HIGH",
      "value_edge": 0.746
    },
    {
      "date": "2026-06-02",
      "player": "Freddy Fermin",
      "team": "San Diego Padres",
      "prop_type": "hits",
      "pick": "UNDER 0.5",
      "projected": 0.28,
      "actual": 0.0,
      "result": "hit",
      "confidence": "HIGH",
      "value_edge": 0.645
    },
    {
      "date": "2026-06-02",
      "player": "Manny Machado",
      "team": "San Diego Padres",
      "prop_type": "hits",
      "pick": "UNDER 0.5",
      "projected": 0.53,
      "actual": 0.0,
      "result": "hit",
      "confidence": "HIGH",
      "value_edge": 0.558
    },
    {
      "date": "2026-06-02",
      "player": "Tyler O'Neill",
      "team": "Baltimore Orioles",
      "prop_type": "hits",
      "pick": "UNDER 0.5",
      "projected": 0.37,
      "actual": 1.0,
      "result": "miss",
      "confidence": "HIGH",
      "value_edge": 0.541
    },
    {
      "date": "2026-06-02",
      "player": "Trea Turner",
      "team": "Philadelphia Phillies",
      "prop_type": "hits",
      "pick": "UNDER 1.5",
      "projected": 0.85,
      "actual": 2.0,
      "result": "miss",
      "confidence": "HIGH",
      "value_edge": 0.532
    },
    {
      "date": "2026-06-02",
      "player": "Zack Short",
      "team": "Detroit Tigers",
      "prop_type": "hits",
      "pick": "UNDER 0.5",
      "projected": 0.2,
      "actual": 2.0,
      "result": "miss",
      "confidence": "HIGH",
      "value_edge": 0.531
    },
    {
      "date": "2026-06-02",
      "player": "Drew Millas",
      "team": "Washington Nationals",
      "prop_type": "hits",
      "pick": "UNDER 0.5",
      "projected": 0.49,
      "actual": 1.0,
      "result": "miss",
      "confidence": "HIGH",
      "value_edge": 0.49
    },
    {
      "date": "2026-06-02",
      "player": "Patrick Bailey",
      "team": "Cleveland Guardians",
      "prop_type": "hits",
      "pick": "UNDER 0.5",
      "projected": 0.36,
      "actual": 1.0,
      "result": "miss",
      "confidence": "HIGH",
      "value_edge": 0.393
    },
    {
      "date": "2026-06-02",
      "player": "Caleb Durbin",
      "team": "Boston Red Sox",
      "prop_type": "hits",
      "pick": "UNDER 0.5",
      "projected": 0.55,
      "actual": 1.0,
      "result": "miss",
      "confidence": "HIGH",
      "value_edge": 0.347
    },
    {
      "date": "2026-06-02",
      "player": "Brayan Rocchio",
      "team": "Cleveland Guardians",
      "prop_type": "hits",
      "pick": "OVER 0.5",
      "projected": 1.02,
      "actual": 1.0,
      "result": "hit",
      "confidence": "HIGH",
      "value_edge": 0.27
    },
    {
      "date": "2026-06-02",
      "player": "Connelly Early",
      "team": "Boston Red Sox",
      "prop_type": "strikeouts_pitcher",
      "pick": "UNDER 5.5",
      "projected": 5.18,
      "actual": 6.0,
      "result": "miss",
      "confidence": "MEDIUM",
      "value_edge": 0.258
    },
    {
      "date": "2026-06-02",
      "player": "Jazz Chisholm Jr.",
      "team": "New York Yankees",
      "prop_type": "hits",
      "pick": "OVER 0.5",
      "projected": 1.11,
      "actual": 1.0,
      "result": "hit",
      "confidence": "HIGH",
      "value_edge": 0.246
    },
    {
      "date": "2026-06-02",
      "player": "Steven Matz",
      "team": "Tampa Bay Rays",
      "prop_type": "strikeouts_pitcher",
      "pick": "UNDER 4.5",
      "projected": 3.89,
      "actual": 2.0,
      "result": "hit",
      "confidence": "HIGH",
      "value_edge": 0.227
    },
    {
      "date": "2026-06-02",
      "player": "Keibert Ruiz",
      "team": "Washington Nationals",
      "prop_type": "hits",
      "pick": "OVER 0.5",
      "projected": 1.15,
      "actual": 0.0,
      "result": "miss",
      "confidence": "HIGH",
      "value_edge": 0.169
    },
    {
      "date": "2026-06-02",
      "player": "James Wood",
      "team": "Washington Nationals",
      "prop_type": "hits",
      "pick": "OVER 0.5",
      "projected": 1.29,
      "actual": 0.0,
      "result": "miss",
      "confidence": "HIGH",
      "value_edge": 0.122
    },
    {
      "date": "2026-06-01",
      "player": "Luinder Avila",
      "team": "Kansas City Royals",
      "prop_type": "strikeouts_pitcher",
      "pick": "OVER 3.5",
      "projected": 9.2,
      "actual": 5.0,
      "result": "hit",
      "confidence": "HIGH",
      "value_edge": 1.154
    },
    {
      "date": "2026-06-01",
      "player": "Shane Drohan",
      "team": "Milwaukee Brewers",
      "prop_type": "strikeouts_pitcher",
      "pick": "OVER 2.5",
      "projected": 12.73,
      "actual": 5.0,
      "result": "hit",
      "confidence": "HIGH",
      "value_edge": 0.995
    },
    {
      "date": "2026-06-01",
      "player": "Griffin Jax",
      "team": "Tampa Bay Rays",
      "prop_type": "strikeouts_pitcher",
      "pick": "UNDER 4.5",
      "projected": 2.88,
      "actual": 5.0,
      "result": "miss",
      "confidence": "HIGH",
      "value_edge": 0.845
    },
    {
      "date": "2026-06-01",
      "player": "Lane Thomas",
      "team": "Kansas City Royals",
      "prop_type": "hits",
      "pick": "UNDER 0.5",
      "projected": 0.43,
      "actual": 3.0,
      "result": "miss",
      "confidence": "HIGH",
      "value_edge": 0.625
    },
    {
      "date": "2026-06-01",
      "player": "Joey Ortiz",
      "team": "Milwaukee Brewers",
      "prop_type": "hits",
      "pick": "UNDER 0.5",
      "projected": 0.34,
      "actual": 1.0,
      "result": "miss",
      "confidence": "HIGH",
      "value_edge": 0.558
    },
    {
      "date": "2026-06-01",
      "player": "Nick Loftin",
      "team": "Kansas City Royals",
      "prop_type": "hits",
      "pick": "UNDER 0.5",
      "projected": 0.41,
      "actual": 1.0,
      "result": "miss",
      "confidence": "HIGH",
      "value_edge": 0.534
    },
    {
      "date": "2026-06-01",
      "player": "Victor Caratini",
      "team": "Minnesota Twins",
      "prop_type": "hits",
      "pick": "UNDER 0.5",
      "projected": 0.47,
      "actual": 1.0,
      "result": "miss",
      "confidence": "HIGH",
      "value_edge": 0.51
    },
    {
      "date": "2026-06-01",
      "player": "Xavier Edwards",
      "team": "Miami Marlins",
      "prop_type": "hits",
      "pick": "OVER 0.5",
      "projected": 1.19,
      "actual": 1.0,
      "result": "hit",
      "confidence": "HIGH",
      "value_edge": 0.429
    },
    {
      "date": "2026-06-01",
      "player": "Jonathan Aranda",
      "team": "Tampa Bay Rays",
      "prop_type": "hits",
      "pick": "OVER 0.5",
      "projected": 1.09,
      "actual": 0.0,
      "result": "miss",
      "confidence": "HIGH",
      "value_edge": 0.37
    },
    {
      "date": "2026-06-01",
      "player": "Zach McKinstry",
      "team": "Detroit Tigers",
      "prop_type": "hits",
      "pick": "UNDER 0.5",
      "projected": 0.38,
      "actual": 1.0,
      "result": "miss",
      "confidence": "HIGH",
      "value_edge": 0.363
    },
    {
      "date": "2026-06-01",
      "player": "Austin Martin",
      "team": "Minnesota Twins",
      "prop_type": "hits",
      "pick": "UNDER 0.5",
      "projected": 0.6,
      "actual": 1.0,
      "result": "miss",
      "confidence": "HIGH",
      "value_edge": 0.363
    },
    {
      "date": "2026-06-01",
      "player": "Jackson Chourio",
      "team": "Milwaukee Brewers",
      "prop_type": "hits",
      "pick": "UNDER 1.5",
      "projected": 1.05,
      "actual": 2.0,
      "result": "miss",
      "confidence": "HIGH",
      "value_edge": 0.349
    },
    {
      "date": "2026-06-01",
      "player": "Joe Ryan",
      "team": "Minnesota Twins",
      "prop_type": "strikeouts_pitcher",
      "pick": "UNDER 6.5",
      "projected": 5.83,
      "actual": 9.0,
      "result": "miss",
      "confidence": "HIGH",
      "value_edge": 0.286
    },
    {
      "date": "2026-06-01",
      "player": "Connor Norby",
      "team": "Miami Marlins",
      "prop_type": "hits",
      "pick": "UNDER 0.5",
      "projected": 0.59,
      "actual": 1.0,
      "result": "miss",
      "confidence": "HIGH",
      "value_edge": 0.23
    },
    {
      "date": "2026-06-01",
      "player": "Joe Mack",
      "team": "Miami Marlins",
      "prop_type": "hits",
      "pick": "UNDER 0.5",
      "projected": 0.57,
      "actual": 1.0,
      "result": "miss",
      "confidence": "HIGH",
      "value_edge": 0.191
    }
  ],
  "last_updated": "2026-06-05T15:53:33.562879+00:00"
}